sdh_pyetl/__init__.py
sdh_pyetl/configs/__init__.py
sdh_pyetl/configs/destination/__init__.py
sdh_pyetl/configs/destination/postgres.py
sdh_pyetl/configs/source/__init__.py
sdh_pyetl/configs/source/s3.py
sdh_pyetl/destination/__init__.py
sdh_pyetl/destination/postgres.py
sdh_pyetl/destination/s3.py
sdh_pyetl/pipeline/__init__.py
sdh_pyetl/source/__init__.py
sdh_pyetl/source/s3.py
sdh_pyetl/utils/__init__.py
sdh_pyetl/utils/data_container.py
sdh_pyetl/utils/exceptions.py
sdh_pyetl/utils/pydantic_helper.py
sdh_pyetl-0.1.2.dist-info/LICENSE
sdh_pyetl-0.1.2.dist-info/METADATA
sdh_pyetl-0.1.2.dist-info/WHEEL
sdh_pyetl-0.1.2.dist-info/RECORD
