Metadata-Version: 2.1
Name: sdh_pyetl
Version: 0.1.2
Summary: A python package to build etl pipeline.
Author: Thomas Menchi
Author-email: thomas.menchi@modeo.ai
Requires-Python: >=3.12.0,<4.0.0
Classifier: Programming Language :: Python :: 3
Classifier: Programming Language :: Python :: 3.12
Requires-Dist: boto3 (>=1.35.76,<2.0.0)
Requires-Dist: loguru (>=0.7.3,<0.8.0)
Requires-Dist: pandas (>=2.2.3,<3.0.0)
Requires-Dist: pydantic (>=2.10.3,<3.0.0)
Requires-Dist: pyyaml (>=6.0.2,<7.0.0)
Requires-Dist: sqlalchemy (>=2.0.36,<3.0.0)
